{
    "info": [], 
    "ratings": "5.0", 
    "website": "", 
    "working_hours": [], 
    "name": "Moonlight Sweet Paan", 
    "claimed_status": "", 
    "url": "https://www.yelp.com/biz/moonlight-sweet-paan-ashburn", 
    "longitude": "-77.480954", 
    "reviews": "1 review", 
    "phone": "(571) 577-3737", 
    "address": "43930 Farmwell Hunt Plz Lotte Plaza Ashburn Ashburn, VA 20147", 
    "latitude": "39.023672", 
    "ratings_histogram": [
        {
            "5 stars": "1"
        }, 
        {
            "4 stars": "0"
        }, 
        {
            "3 stars": "0"
        }, 
        {
            "2 stars": "0"
        }, 
        {
            "1 star": "0"
        }
    ], 
    "price_range": "", 
    "health_rating": "", 
    "category": "Pakistani,Indian"
}