{
    "info": [
        {
            "Takes Reservations": "Yes"
        }, 
        {
            "Delivery": "Yes"
        }, 
        {
            "Take-out": "Yes"
        }, 
        {
            "Accepts Credit Cards": "Yes"
        }, 
        {
            "Good For": "Lunch, Dinner"
        }, 
        {
            "Parking": "Private Lot"
        }, 
        {
            "Bike Parking": "Yes"
        }, 
        {
            "Good for Kids": "Yes"
        }, 
        {
            "Good for Groups": "Yes"
        }, 
        {
            "Attire": "Casual"
        }, 
        {
            "Ambience": "Casual"
        }, 
        {
            "Noise Level": "Quiet"
        }, 
        {
            "Alcohol": "Full Bar"
        }, 
        {
            "Outdoor Seating": "No"
        }, 
        {
            "Wi-Fi": "No"
        }, 
        {
            "Has TV": "No"
        }, 
        {
            "Caters": "Yes"
        }
    ], 
    "ratings": "3.0", 
    "website": "http://www.preetpalace.com", 
    "working_hours": [
        {
            "Mon": "11:30 am - 10:00 pm"
        }, 
        {
            "Tue": "11:30 am - 10:00 pm\n        \n                Open now"
        }, 
        {
            "Wed": "11:30 am - 10:00 pm"
        }, 
        {
            "Thu": "11:30 am - 10:00 pm"
        }, 
        {
            "Fri": "11:30 am - 10:30 pm"
        }, 
        {
            "Sat": "12:00 pm - 10:30 pm"
        }, 
        {
            "Sun": "12:00 pm - 10:00 pm"
        }
    ], 
    "name": "Preet Palace", 
    "claimed_status": "Claimed", 
    "url": "https://www.yelp.com/biz/preet-palace-centreville", 
    "longitude": "-77.433775", 
    "reviews": "80 reviews", 
    "phone": "(703) 815-4500", 
    "address": "14112 Lee Hwy Centreville, VA 20120", 
    "latitude": "38.839692", 
    "ratings_histogram": [
        {
            "5 stars": "13"
        }, 
        {
            "4 stars": "28"
        }, 
        {
            "3 stars": "13"
        }, 
        {
            "2 stars": "10"
        }, 
        {
            "1 star": "16"
        }
    ], 
    "price_range": "$11-30", 
    "health_rating": "", 
    "category": "Indian,Barbeque,Soup"
}